shortier/__init__.py
shortier/cli.py
shortier/shortier.py
shortier-1.1.3.dist-info/LICENSE
shortier-1.1.3.dist-info/METADATA
shortier-1.1.3.dist-info/WHEEL
shortier-1.1.3.dist-info/entry_points.txt
shortier-1.1.3.dist-info/top_level.txt
shortier-1.1.3.dist-info/RECORD
